{
  "$schema": "https://ui.shadcn.com/schema/registry-item.json",
  "name": "feedback-form",
  "type": "registry:ui",
  "title": "Feedback Form",
  "description": "A highly customizable neo-brutalist Feedback Form component built with Brutx design tokens for Vue 3.",
  "dependencies": [
    "lucide-vue-next"
  ],
  "registryDependencies": [
    "card",
    "input",
    "textarea",
    "button"
  ],
  "files": [
    {
      "path": "components/ui/feedback-form/FeedbackForm.vue",
      "content": "<script setup lang=\"ts\">\nimport { computed, ref } from 'vue'\nimport { Send } from 'lucide-vue-next'\nimport { cn } from '@/lib/utils'\nimport { useLocale } from '@/composables/useLocale'\nimport Card from '@/components/ui/card/Card.vue'\nimport CardHeader from '@/components/ui/card/CardHeader.vue'\nimport CardContent from '@/components/ui/card/CardContent.vue'\nimport CardTitle from '@/components/ui/card/CardTitle.vue'\nimport CardDescription from '@/components/ui/card/CardDescription.vue'\nimport Input from '@/components/ui/input/Input.vue'\nimport Textarea from '@/components/ui/textarea/Textarea.vue'\nimport Button from '@/components/ui/button/Button.vue'\n\ninterface FeedbackFormProps {\n    title?: string\n    description?: string\n    submitText?: string\n    class?: string\n}\n\nconst props = withDefaults(defineProps<FeedbackFormProps>(), {\n    title: undefined,\n    description: undefined,\n    submitText: undefined,\n    class: '',\n})\n\nconst emit = defineEmits<{\n    submit: [payload: { name: string; email: string; subject: string; message: string }]\n}>()\n\nconst { t } = useLocale()\n\nconst resolvedTitle = computed(() => props.title ?? t('feedbackForm.defaultTitle'))\nconst resolvedDescription = computed(() => props.description ?? t('feedbackForm.defaultDescription'))\nconst resolvedSubmitText = computed(() => props.submitText ?? t('feedbackForm.defaultSubmitText'))\nconst nameLabel = computed(() => t('feedbackForm.nameLabel'))\nconst emailLabel = computed(() => t('feedbackForm.emailLabel'))\nconst subjectLabel = computed(() => t('feedbackForm.subjectLabel'))\nconst messageLabel = computed(() => t('feedbackForm.messageLabel'))\n\nconst name = ref('')\nconst email = ref('')\nconst subject = ref('')\nconst message = ref('')\n\nconst rootClasses = computed(() => cn('w-full max-w-2xl mx-auto', props.class))\n\nfunction handleSubmit() {\n    emit('submit', {\n        name: name.value,\n        email: email.value,\n        subject: subject.value,\n        message: message.value,\n    })\n}\n</script>\n\n<template>\n    <div :class=\"rootClasses\">\n        <slot name=\"header\">\n            <div class=\"text-center mb-8\">\n                <h2 class=\"text-3xl font-black tracking-tight\">\n                    {{ resolvedTitle }}\n                </h2>\n                <p v-if=\"resolvedDescription\" class=\"mt-2 text-brutal-muted-foreground font-medium\">\n                    {{ resolvedDescription }}\n                </p>\n            </div>\n        </slot>\n\n        <slot>\n            <Card variant=\"default\">\n                <CardHeader>\n                    <CardTitle class=\"text-xl\">\n                        {{ resolvedTitle }}\n                    </CardTitle>\n                    <CardDescription v-if=\"resolvedDescription\">\n                        {{ resolvedDescription }}\n                    </CardDescription>\n                </CardHeader>\n                <CardContent>\n                    <form class=\"space-y-4\" @submit.prevent=\"handleSubmit\">\n                        <div class=\"space-y-2\">\n                            <label class=\"text-sm font-bold text-brutal-fg\">\n                                {{ nameLabel }}\n                            </label>\n                            <Input v-model=\"name\" :placeholder=\"nameLabel\" />\n                        </div>\n                        <div class=\"space-y-2\">\n                            <label class=\"text-sm font-bold text-brutal-fg\">\n                                {{ emailLabel }}\n                            </label>\n                            <Input v-model=\"email\" type=\"email\" :placeholder=\"emailLabel\" />\n                        </div>\n                        <div class=\"space-y-2\">\n                            <label class=\"text-sm font-bold text-brutal-fg\">\n                                {{ subjectLabel }}\n                            </label>\n                            <Input v-model=\"subject\" :placeholder=\"subjectLabel\" />\n                        </div>\n                        <div class=\"space-y-2\">\n                            <label class=\"text-sm font-bold text-brutal-fg\">\n                                {{ messageLabel }}\n                            </label>\n                            <Textarea v-model=\"message\" :placeholder=\"messageLabel\" />\n                        </div>\n                        <Button variant=\"primary\" type=\"submit\" class=\"w-full\">\n                            <Send class=\"h-4 w-4 mr-2\" />\n                            {{ resolvedSubmitText }}\n                        </Button>\n                    </form>\n                </CardContent>\n            </Card>\n        </slot>\n\n        <slot name=\"footer\" />\n    </div>\n</template>\n",
      "type": "registry:ui"
    }
  ],
  "tailwind": {
    "config": {
      "theme": {
        "extend": {
          "borderWidth": {
            "3": "var(--brutal-border-width, 3px)"
          },
          "borderColor": {
            "brutal": "var(--brutal-border-color, #000000)"
          },
          "borderRadius": {
            "brutal": "var(--brutal-radius, 0px)"
          },
          "colors": {
            "brutal-bg": "var(--brutal-bg, #ffffff)",
            "brutal-fg": "var(--brutal-fg, #000000)",
            "brutal-primary": "var(--brutal-primary, #FF6B6B)",
            "brutal-secondary": "var(--brutal-secondary, #4ECDC4)",
            "brutal-accent": "var(--brutal-accent, #FFE66D)",
            "brutal-destructive": "var(--brutal-destructive, #EF476F)",
            "brutal-success": "var(--brutal-success, #7FB069)",
            "brutal-muted": "var(--brutal-muted, #f3f4f6)",
            "brutal-ring": "var(--brutal-ring, #000000)",
            "brutal-info": "var(--brutal-info, #4A90D9)",
            "brutal-muted-foreground": "var(--brutal-muted-foreground, #4B5563)",
            "brutal-overlay": "var(--brutal-overlay, rgba(0, 0, 0, 0.5))",
            "brutal-placeholder": "var(--brutal-placeholder, #9CA3AF)"
          },
          "boxShadow": {
            "brutal": "var(--brutal-shadow-offset-x, 4px) var(--brutal-shadow-offset-y, 4px) 0px 0px var(--brutal-shadow-color, #000000)",
            "brutal-sm": "calc(var(--brutal-shadow-offset-x, 4px) / 2) calc(var(--brutal-shadow-offset-y, 4px) / 2) 0px 0px var(--brutal-shadow-color, #000000)",
            "brutal-lg": "calc(var(--brutal-shadow-offset-x, 4px) * 1.5) calc(var(--brutal-shadow-offset-y, 4px) * 1.5) 0px 0px var(--brutal-shadow-color, #000000)",
            "brutal-xl": "calc(var(--brutal-shadow-offset-x, 4px) * 2) calc(var(--brutal-shadow-offset-y, 4px) * 2) 0px 0px var(--brutal-shadow-color, #000000)"
          }
        }
      }
    }
  },
  "cssVars": {
    "light": {
      "brutal-border-width": "3px",
      "brutal-border-color": "#000000",
      "brutal-shadow-offset-x": "4px",
      "brutal-shadow-offset-y": "4px",
      "brutal-shadow-color": "#000000",
      "brutal-radius": "0px",
      "brutal-pressed-offset": "2px",
      "brutal-bg": "#ffffff",
      "brutal-fg": "#000000",
      "brutal-primary": "#FF6B6B",
      "brutal-secondary": "#4ECDC4",
      "brutal-accent": "#FFE66D",
      "brutal-destructive": "#EF476F",
      "brutal-success": "#7FB069",
      "brutal-muted": "#f3f4f6",
      "brutal-ring": "#000000",
      "brutal-info": "#4A90D9",
      "brutal-muted-foreground": "#4B5563",
      "brutal-overlay": "rgba(0, 0, 0, 0.5)",
      "brutal-placeholder": "#9CA3AF"
    },
    "dark": {
      "brutal-border-width": "3px",
      "brutal-border-color": "#ffffff",
      "brutal-shadow-offset-x": "4px",
      "brutal-shadow-offset-y": "4px",
      "brutal-shadow-color": "#ffffff",
      "brutal-radius": "0px",
      "brutal-pressed-offset": "2px",
      "brutal-bg": "#141414",
      "brutal-fg": "#ffffff",
      "brutal-primary": "#FF6B6B",
      "brutal-secondary": "#4ECDC4",
      "brutal-accent": "#FFE66D",
      "brutal-destructive": "#EF476F",
      "brutal-success": "#7FB069",
      "brutal-muted": "#1e1e1e",
      "brutal-ring": "#ffffff",
      "brutal-info": "#3B82F6",
      "brutal-muted-foreground": "#9CA3AF",
      "brutal-overlay": "rgba(0, 0, 0, 0.7)",
      "brutal-placeholder": "#6B7280"
    }
  }
}