{
  "$schema": "https://ui.shadcn.com/schema/registry-item.json",
  "name": "kbd",
  "type": "registry:ui",
  "title": "Kbd",
  "description": "Keyboard shortcut key display element.",
  "category": "utility",
  "examples": [],
  "dependencies": [],
  "registryDependencies": [],
  "files": [
    {
      "path": "components/ui/kbd/Kbd.vue",
      "content": "<script setup lang=\"ts\">\nimport { computed } from 'vue';\nimport { type VariantProps } from 'class-variance-authority';\nimport { cn } from '@/lib/utils';\nimport { kbdVariants } from '@/components/ui/kbd/kbd-variants';\n\ntype KbdVariantProps = VariantProps<typeof kbdVariants>;\n\ninterface KbdProps {\n    variant?: NonNullable<KbdVariantProps['variant']>;\n    size?: NonNullable<KbdVariantProps['size']>;\n    class?: string;\n}\n\nconst props = withDefaults(defineProps<KbdProps>(), {\n    variant: 'default',\n    size: 'md',\n    class: undefined,\n});\n\nconst classes = computed(() =>\n    cn(kbdVariants({ variant: props.variant, size: props.size }), props.class)\n);\n</script>\n\n<template>\n    <kbd :class=\"classes\">\n        <slot />\n    </kbd>\n</template>\n",
      "type": "registry:ui"
    },
    {
      "path": "components/ui/kbd/kbd-variants.ts",
      "content": "import { cva } from 'class-variance-authority'\nimport { chipBaseClasses, chipColorVariants } from '@/lib/chip-variants'\n\nexport const kbdVariants = cva(\n    [\n        ...chipBaseClasses,\n        'justify-center',\n        'font-mono font-black',\n        'shadow-brutal-sm',\n        'select-none whitespace-nowrap',\n    ],\n    {\n        variants: {\n            variant: {\n                default: 'bg-brutal-muted text-brutal-fg',\n                primary: chipColorVariants.primary,\n                secondary: chipColorVariants.secondary,\n                accent: chipColorVariants.accent,\n            },\n            size: {\n                sm: 'px-1.5 py-0.5 text-xs min-w-[1.25rem]',\n                md: 'px-2 py-1 text-sm min-w-[1.75rem]',\n                lg: 'px-3 py-1.5 text-base min-w-[2.25rem]',\n            },\n        },\n        defaultVariants: {\n            variant: 'default',\n            size: 'md',\n        },\n    }\n)\n",
      "type": "registry:lib"
    },
    {
      "path": "components/ui/kbd/index.ts",
      "content": "/**\n * AUTO-GENERATED by prebuild — DO NOT EDIT.\n * To add public exports, edit the underlying .vue/.ts file (it will be\n * picked up automatically on the next prebuild).\n */\n\nexport { default as Kbd } from '@/components/ui/kbd/Kbd.vue'\nexport type * from '@/components/ui/kbd/Kbd.vue'\nexport * from '@/components/ui/kbd/kbd-variants'\n",
      "type": "registry:ui"
    },
    {
      "path": "lib/chip-variants.ts",
      "content": "export const chipBaseClasses = [\n    'inline-flex items-center',\n    'border-3 border-brutal',\n    'rounded-brutal',\n] as const\n\nexport const chipColorVariants = {\n    primary: 'bg-brutal-primary text-brutal-primary-foreground',\n    secondary: 'bg-brutal-secondary text-brutal-secondary-foreground',\n    accent: 'bg-brutal-accent text-brutal-accent-foreground',\n} as const\n",
      "type": "registry:lib"
    }
  ],
  "tailwind": {},
  "cssVars": {
    "light": {
      "brutal-border-width": "3px",
      "brutal-border-color": "#000000",
      "brutal-shadow-offset-x": "4px",
      "brutal-shadow-offset-y": "4px",
      "brutal-shadow-color": "#000000",
      "brutal-radius": "0px",
      "brutal-pressed-offset": "2px",
      "brutal-bg": "#ffffff",
      "brutal-fg": "#000000",
      "brutal-primary": "#FF6B6B",
      "brutal-primary-foreground": "#000000",
      "brutal-secondary": "#4ECDC4",
      "brutal-secondary-foreground": "#000000",
      "brutal-accent": "#FFE66D",
      "brutal-accent-foreground": "#000000",
      "brutal-destructive": "#EF476F",
      "brutal-destructive-foreground": "#ffffff",
      "brutal-success": "#7FB069",
      "brutal-success-foreground": "#000000",
      "brutal-muted": "#f3f4f6",
      "brutal-muted-foreground": "#4B5563",
      "brutal-ring": "#000000",
      "brutal-info": "#4A90D9",
      "brutal-info-foreground": "#ffffff",
      "brutal-overlay": "rgba(0, 0, 0, 0.5)",
      "brutal-placeholder": "#9CA3AF",
      "brutal-black": "#000000",
      "brutal-yellow": "#FFE66D"
    },
    "dark": {
      "brutal-border-width": "3px",
      "brutal-border-color": "#ffffff",
      "brutal-shadow-offset-x": "4px",
      "brutal-shadow-offset-y": "4px",
      "brutal-shadow-color": "#ffffff",
      "brutal-radius": "0px",
      "brutal-pressed-offset": "2px",
      "brutal-bg": "#141414",
      "brutal-fg": "#ffffff",
      "brutal-primary": "#FF6B6B",
      "brutal-primary-foreground": "#000000",
      "brutal-secondary": "#4ECDC4",
      "brutal-secondary-foreground": "#000000",
      "brutal-accent": "#FFE66D",
      "brutal-accent-foreground": "#000000",
      "brutal-destructive": "#EF476F",
      "brutal-destructive-foreground": "#ffffff",
      "brutal-success": "#7FB069",
      "brutal-success-foreground": "#000000",
      "brutal-muted": "#1e1e1e",
      "brutal-muted-foreground": "#9CA3AF",
      "brutal-ring": "#ffffff",
      "brutal-info": "#3B82F6",
      "brutal-info-foreground": "#ffffff",
      "brutal-overlay": "rgba(0, 0, 0, 0.7)",
      "brutal-placeholder": "#6B7280",
      "brutal-black": "#000000",
      "brutal-yellow": "#FFE66D"
    }
  },
  "integrity": "sha256-c2fec2a519cb4f85df2ee263736756ebb602ee4a368d183e3dd648b225ca2131"
}