{
  "$schema": "https://lidaixingchen.github.io/brutxui-vue3/registry-manifest.schema.json",
  "name": "brutx-vue",
  "schemaVersion": 1,
  "registryVersion": "0.1.0",
  "buildTimestamp": null,
  "gitCommit": null,
  "itemCount": 87,
  "items": {
    "accordion": {
      "integrity": "sha256-7878f891c2acfc679da45a20f44b03ccd8a12c408e750a88fae179a86268e678",
      "fileCount": 8,
      "dependencies": [
        "@lucide/vue",
        "reka-ui"
      ],
      "registryDependencies": [],
      "category": "navigation",
      "examples": []
    },
    "alert": {
      "integrity": "sha256-fa17ce9912bfaed1ca499f4788454b4e118b2240a13a29e75e901e7124f755f7",
      "fileCount": 6,
      "dependencies": [
        "@lucide/vue"
      ],
      "registryDependencies": [
        "button",
        "locale-zh-cn"
      ],
      "category": "feedback",
      "examples": []
    },
    "alert-dialog": {
      "integrity": "sha256-6bf581e1d03e683545dcba24fddde2b3ab38963d3b56a239190b32e0a6af365f",
      "fileCount": 11,
      "dependencies": [
        "reka-ui"
      ],
      "registryDependencies": [
        "button"
      ],
      "category": "overlay",
      "examples": []
    },
    "auth-card": {
      "integrity": "sha256-adb5747d2391f7e8235e093477f1fe486b8af2c0d135a41b3dd034afdbfbc8f7",
      "fileCount": 4,
      "dependencies": [
        "@lucide/vue"
      ],
      "registryDependencies": [
        "button",
        "card",
        "input",
        "label",
        "locale-zh-cn"
      ],
      "category": "layout",
      "examples": []
    },
    "avatar": {
      "integrity": "sha256-9e535a67c88226ceea76a2a19dbe9ba68f66fda2d8e7ca38e65f0a756528aba9",
      "fileCount": 6,
      "dependencies": [
        "reka-ui"
      ],
      "registryDependencies": [
        "locale-zh-cn"
      ],
      "category": "data-display",
      "examples": []
    },
    "backtop": {
      "integrity": "sha256-d42245522e731fb709a6d57414cf16069cd02385d7c99e7476d0f117699693a7",
      "fileCount": 2,
      "dependencies": [
        "@lucide/vue"
      ],
      "registryDependencies": [
        "button"
      ],
      "category": "navigation",
      "examples": []
    },
    "badge": {
      "integrity": "sha256-019ecfef8b26ed208f49ef0a50e1f802dcfbbeb38bf4b82fedee04a637584e0d",
      "fileCount": 5,
      "dependencies": [],
      "registryDependencies": [
        "locale-zh-cn"
      ],
      "category": "feedback",
      "examples": []
    },
    "before-after": {
      "integrity": "sha256-0c1f98f4a41795b922a9866a565f3adf8d36298077372d02836853e6bbd9a4ad",
      "fileCount": 6,
      "dependencies": [
        "@lucide/vue"
      ],
      "registryDependencies": [
        "locale-zh-cn"
      ],
      "category": "visual-effect",
      "examples": []
    },
    "breadcrumb": {
      "integrity": "sha256-66d70380c98976530296c4c8e2fa4c56d48ebd15ff490b9d6c1fc5be772f7a68",
      "fileCount": 11,
      "dependencies": [
        "@lucide/vue",
        "reka-ui"
      ],
      "registryDependencies": [
        "locale-zh-cn"
      ],
      "category": "navigation",
      "examples": []
    },
    "brutalist-hero": {
      "integrity": "sha256-55d906a533c2a4c56a68d9dff71175184cd01e839dddd6c6b60c8f3dd9393814",
      "fileCount": 3,
      "dependencies": [
        "@lucide/vue"
      ],
      "registryDependencies": [
        "badge",
        "button",
        "card",
        "locale-zh-cn"
      ],
      "category": "marketing",
      "examples": []
    },
    "button": {
      "integrity": "sha256-ba37ead5b78ee48ff905284524e7f269e1e596fc1af89d005fc3e1d91dd7e25d",
      "fileCount": 11,
      "dependencies": [
        "@lucide/vue",
        "reka-ui"
      ],
      "registryDependencies": [
        "locale-zh-cn"
      ],
      "category": "action",
      "examples": []
    },
    "calendar": {
      "integrity": "sha256-230c2f7c843f8a0489a269afc1a155c1e0e0004c26e8404b8188048d9d5ce1b2",
      "fileCount": 4,
      "dependencies": [
        "@lucide/vue",
        "v-calendar"
      ],
      "registryDependencies": [
        "tooltip"
      ],
      "category": "data-display",
      "examples": []
    },
    "card": {
      "integrity": "sha256-d340ac68167d967573a463738a04aaa2500b784e9669f781ad7a391a4335641c",
      "fileCount": 8,
      "dependencies": [],
      "registryDependencies": [],
      "category": "layout",
      "examples": []
    },
    "card-3d": {
      "integrity": "sha256-0de50eab9825ae645e5d823d8971e63baddd592848740ab3f0f5fa323f693b78",
      "fileCount": 6,
      "dependencies": [],
      "registryDependencies": [
        "locale-zh-cn"
      ],
      "category": "layout",
      "examples": []
    },
    "carousel": {
      "integrity": "sha256-92df69eedbc0e9c473f37c2a23c3955fcf03993a8601c23feac0984505ccde06",
      "fileCount": 12,
      "dependencies": [
        "@lucide/vue",
        "embla-carousel-vue"
      ],
      "registryDependencies": [
        "button",
        "locale-zh-cn"
      ],
      "category": "data-display",
      "examples": []
    },
    "cascader": {
      "integrity": "sha256-d5f034fb294088a22d8ec3c6c16adec3b3df66ab80f163ba27903bfb98c25b85",
      "fileCount": 11,
      "dependencies": [
        "@lucide/vue",
        "reka-ui"
      ],
      "registryDependencies": [
        "checkbox",
        "locale-zh-cn",
        "popover"
      ],
      "category": "form",
      "examples": []
    },
    "chat-bubble": {
      "integrity": "sha256-07aae0628336b63242382feb6af983dc3f4a949e78dba4d87b04e5611dd04b8a",
      "fileCount": 5,
      "dependencies": [
        "@lucide/vue",
        "reka-ui"
      ],
      "registryDependencies": [
        "locale-zh-cn"
      ],
      "category": "data-display",
      "examples": []
    },
    "checkbox": {
      "integrity": "sha256-3cc01b8b8565c1497950583e235ee3bd2396b84527e7a47c7af0e81db86ce354",
      "fileCount": 6,
      "dependencies": [
        "@lucide/vue",
        "reka-ui"
      ],
      "registryDependencies": [
        "locale-zh-cn"
      ],
      "category": "form",
      "examples": []
    },
    "code-block": {
      "integrity": "sha256-9cd462e4ff67e0658b4e5f0e2672a6a9cb2dbd3b09f2f554089b30c02fc23d65",
      "fileCount": 6,
      "dependencies": [
        "@lucide/vue",
        "prismjs"
      ],
      "registryDependencies": [
        "button",
        "copy-to-clipboard",
        "locale-zh-cn"
      ],
      "category": "data-display",
      "examples": []
    },
    "color-mode-switcher": {
      "integrity": "sha256-afe717844b172897951a12c3d3afd4dfd71460da434d4ff775f494f425816823",
      "fileCount": 4,
      "dependencies": [
        "@lucide/vue"
      ],
      "registryDependencies": [
        "button",
        "locale-zh-cn",
        "select"
      ],
      "category": "utility",
      "examples": []
    },
    "color-picker": {
      "integrity": "sha256-a848dbe9bc5c48559df8d98b85607afea87a7c4faaa3e790b4e7c4ccd7cbb39b",
      "fileCount": 15,
      "dependencies": [
        "@lucide/vue",
        "reka-ui"
      ],
      "registryDependencies": [
        "button",
        "locale-zh-cn",
        "popover"
      ],
      "category": "form",
      "examples": []
    },
    "combobox": {
      "integrity": "sha256-c0431d9882c2b5dbc6f25f18614e283c449a7aec54494cd41e60be876e4ebef6",
      "fileCount": 7,
      "dependencies": [
        "@lucide/vue",
        "reka-ui"
      ],
      "registryDependencies": [
        "button",
        "command",
        "locale-zh-cn",
        "popover",
        "spinner"
      ],
      "category": "form",
      "examples": []
    },
    "command": {
      "integrity": "sha256-3fa3cc32f5f8e5c3aa99e758c98bfd6567b133ee8af8f58253cd6dc64223e77e",
      "fileCount": 13,
      "dependencies": [
        "reka-ui"
      ],
      "registryDependencies": [
        "dialog",
        "locale-zh-cn"
      ],
      "category": "overlay",
      "examples": []
    },
    "cookie-consent": {
      "integrity": "sha256-6546322222c4f700281215493371eedd64f6c52b70c62398d4d7962fb6ae5d6f",
      "fileCount": 3,
      "dependencies": [
        "@lucide/vue"
      ],
      "registryDependencies": [
        "button",
        "card",
        "locale-zh-cn"
      ],
      "category": "marketing",
      "examples": []
    },
    "copy-to-clipboard": {
      "integrity": "sha256-0fd861cafbad03445bad99584862d6f615cde82372c3ce56535abcebf9852b7a",
      "fileCount": 6,
      "dependencies": [
        "@lucide/vue"
      ],
      "registryDependencies": [
        "locale-zh-cn"
      ],
      "category": "utility",
      "examples": []
    },
    "counter": {
      "integrity": "sha256-3168b3921963de32218064380e2d4d52b72c1cc68b44ccb2f230da360ceff0cc",
      "fileCount": 4,
      "dependencies": [],
      "registryDependencies": [],
      "category": "data-display",
      "examples": []
    },
    "dashboard-shell": {
      "integrity": "sha256-0290d91480cb7d0fd53384f5b0fd2ba5a9c1f06c9245292bb359e4d8b3829f42",
      "fileCount": 3,
      "dependencies": [
        "@lucide/vue"
      ],
      "registryDependencies": [
        "button",
        "locale-zh-cn"
      ],
      "category": "layout",
      "examples": []
    },
    "data-table": {
      "integrity": "sha256-4fd9de67b233e50e2cd8c4e22a4d7e4fd926581c61e09d07a45c7359b3038a26",
      "fileCount": 13,
      "dependencies": [
        "@lucide/vue"
      ],
      "registryDependencies": [
        "button",
        "checkbox",
        "input",
        "locale-zh-cn",
        "popover",
        "select",
        "virtual-scroll"
      ],
      "category": "data-display",
      "examples": []
    },
    "date-picker": {
      "integrity": "sha256-738b9990e35442fc02c1c4a0d27bea7c953b8590ce554872cbfec394aa886ffb",
      "fileCount": 23,
      "dependencies": [
        "@lucide/vue",
        "reka-ui",
        "v-calendar"
      ],
      "registryDependencies": [
        "button",
        "locale-zh-cn",
        "popover",
        "select"
      ],
      "category": "form",
      "examples": []
    },
    "descriptions": {
      "integrity": "sha256-629c454456e6e6fbc65a37033c3a5c3221a1d428977dbb5a3ed872a14c06f6cc",
      "fileCount": 3,
      "dependencies": [],
      "registryDependencies": [],
      "category": "data-display",
      "examples": []
    },
    "dialog": {
      "integrity": "sha256-0f75f8921c577b9f0f2a4e16136aa87e845a5c7b4fa7276db3c33331ae23cdcd",
      "fileCount": 17,
      "dependencies": [
        "@lucide/vue",
        "reka-ui"
      ],
      "registryDependencies": [
        "button",
        "input",
        "locale-zh-cn"
      ],
      "category": "overlay",
      "examples": []
    },
    "dropdown-menu": {
      "integrity": "sha256-706ef68d4c014b09b8547c5a6ef37ce01bd95f464fcbdd396884653dc4b4c891",
      "fileCount": 14,
      "dependencies": [
        "@lucide/vue",
        "reka-ui"
      ],
      "registryDependencies": [],
      "category": "overlay",
      "examples": []
    },
    "feedback-form": {
      "integrity": "sha256-f93e16ac0f0fd656c5bdd7e56fc3f6bd7d39a062cdf5243866b91cfd6608bce4",
      "fileCount": 3,
      "dependencies": [
        "@lucide/vue"
      ],
      "registryDependencies": [
        "button",
        "card",
        "input",
        "label",
        "locale-zh-cn",
        "result",
        "textarea"
      ],
      "category": "marketing",
      "examples": []
    },
    "footer-section": {
      "integrity": "sha256-5aaec348fd773c555a275c6419a116a3d3fe74dc1bf29172832fb410b3ee5392",
      "fileCount": 3,
      "dependencies": [
        "@lucide/vue"
      ],
      "registryDependencies": [
        "button",
        "locale-zh-cn",
        "separator"
      ],
      "category": "marketing",
      "examples": []
    },
    "form": {
      "integrity": "sha256-1f3a2225c0aee50f3cc712d11ed872b1c161e99629421ac24023267025e46062",
      "fileCount": 14,
      "dependencies": [
        "reka-ui",
        "vee-validate"
      ],
      "registryDependencies": [
        "button",
        "label",
        "locale-zh-cn",
        "stepper"
      ],
      "category": "form",
      "examples": []
    },
    "glitch-text": {
      "integrity": "sha256-0215576d34aecbd80cb2d5885ff80d3e53e899e04e12e83c9e3962eed0150246",
      "fileCount": 6,
      "dependencies": [],
      "registryDependencies": [],
      "category": "visual-effect",
      "examples": []
    },
    "hardcore-input": {
      "integrity": "sha256-661fc6c33947459acd5021286395f8bcbf963151f0dd907c53ba2fcfcab7b3f5",
      "fileCount": 7,
      "dependencies": [],
      "registryDependencies": [
        "form",
        "input",
        "locale-zh-cn"
      ],
      "category": "form",
      "examples": []
    },
    "header-section": {
      "integrity": "sha256-7ff13c18f600fc47b7d7af4e6bdf2c8b5acabf0b92f894b403e0591122e0936f",
      "fileCount": 4,
      "dependencies": [
        "@lucide/vue",
        "reka-ui"
      ],
      "registryDependencies": [
        "button",
        "locale-zh-cn",
        "separator",
        "sheet"
      ],
      "category": "marketing",
      "examples": []
    },
    "image": {
      "integrity": "sha256-d699a712f7a2020a0dc432e2f7a749c0446b352770b3acaa3d34704081ca0b40",
      "fileCount": 3,
      "dependencies": [
        "@lucide/vue",
        "reka-ui"
      ],
      "registryDependencies": [],
      "category": "data-display",
      "examples": []
    },
    "infinite-scroll": {
      "integrity": "sha256-d0446d08017aaaee77aca33c24ad7a9525342f90d9a78545caf691e1cd172e5a",
      "fileCount": 4,
      "dependencies": [],
      "registryDependencies": [],
      "category": "utility",
      "examples": []
    },
    "input": {
      "integrity": "sha256-fc6c7471961844b6b54c4e4705616442b7cb5dab2a059c0d39a63abbf3f160f6",
      "fileCount": 6,
      "dependencies": [],
      "registryDependencies": [
        "locale-zh-cn"
      ],
      "category": "form",
      "examples": []
    },
    "kanban": {
      "integrity": "sha256-03594f868f421cde738ba0fd31d511c65fa2d67e4a5fea42d54cff5d22288005",
      "fileCount": 6,
      "dependencies": [
        "@lucide/vue"
      ],
      "registryDependencies": [
        "button",
        "locale-zh-cn"
      ],
      "category": "utility",
      "examples": []
    },
    "kbd": {
      "integrity": "sha256-63839fb061e0036337d33b8158a763e458f52b854aa9866b85d417e55a63f669",
      "fileCount": 3,
      "dependencies": [],
      "registryDependencies": [],
      "category": "utility",
      "examples": []
    },
    "label": {
      "integrity": "sha256-feb41e154e6931801ad88e6285674cace19892ef86621c8a506e830c39b6c2d9",
      "fileCount": 2,
      "dependencies": [
        "reka-ui"
      ],
      "registryDependencies": [],
      "category": "form",
      "examples": []
    },
    "loading": {
      "integrity": "sha256-82c439c9d559de1d4e960096b375520c9615d97695623cc409628bd5960ca5d1",
      "fileCount": 3,
      "dependencies": [],
      "registryDependencies": [
        "progress",
        "skeleton",
        "spinner"
      ],
      "category": "feedback",
      "examples": []
    },
    "locale-zh-cn": {
      "integrity": "sha256-54cdbd4f683c559f9e6dad45ba15ae796b077ac695430bd3baff449b5af0e0d1",
      "fileCount": 2,
      "dependencies": [],
      "registryDependencies": [],
      "examples": []
    },
    "marquee": {
      "integrity": "sha256-c839e6019d866a77b6270eb91bc91ff1a872d7ca8798d3ec16ba3d31fa46668f",
      "fileCount": 4,
      "dependencies": [],
      "registryDependencies": [],
      "category": "visual-effect",
      "examples": []
    },
    "menu": {
      "integrity": "sha256-8bb40a671f31ae20bc6fdaad6a0a4d293e7b80281bbc96187dd84d3d1fc46b99",
      "fileCount": 6,
      "dependencies": [
        "@lucide/vue"
      ],
      "registryDependencies": [],
      "category": "navigation",
      "examples": []
    },
    "message": {
      "integrity": "sha256-651a2b89a0395f7713d55c692c9d05bfce56403cab0460bc6076709befd48ade",
      "fileCount": 8,
      "dependencies": [
        "@lucide/vue"
      ],
      "registryDependencies": [
        "button",
        "locale-zh-cn"
      ],
      "category": "feedback",
      "examples": []
    },
    "noise-background": {
      "integrity": "sha256-142a504bea780d51c4cff05d85c96fd49c5e821617c039e37aea629d3bde091e",
      "fileCount": 4,
      "dependencies": [],
      "registryDependencies": [],
      "category": "visual-effect",
      "examples": []
    },
    "number-input": {
      "integrity": "sha256-966574a2c3f5b1dbd9df66ac9ee68a11ccb9fd060d4aac6d4c628a2605457380",
      "fileCount": 5,
      "dependencies": [
        "@lucide/vue",
        "reka-ui"
      ],
      "registryDependencies": [
        "input",
        "locale-zh-cn"
      ],
      "category": "form",
      "examples": []
    },
    "pagination": {
      "integrity": "sha256-4e60f653540dfebd186c7fbc0d5b4e824b4b70128c254476a57c366b04fd7501",
      "fileCount": 5,
      "dependencies": [
        "@lucide/vue"
      ],
      "registryDependencies": [
        "input",
        "locale-zh-cn",
        "select"
      ],
      "category": "navigation",
      "examples": []
    },
    "popconfirm": {
      "integrity": "sha256-36d486920188e17f27b9bc457c2a2de8d51a13e45b4ac374447e2198d9f2d225",
      "fileCount": 2,
      "dependencies": [
        "@lucide/vue"
      ],
      "registryDependencies": [
        "locale-zh-cn"
      ],
      "category": "overlay",
      "examples": []
    },
    "popover": {
      "integrity": "sha256-dcfc2cb7e5f409dc6c9cd02752ce862ed59f0078968268d12d0ed4c5a0aab530",
      "fileCount": 7,
      "dependencies": [
        "reka-ui"
      ],
      "registryDependencies": [],
      "category": "overlay",
      "examples": []
    },
    "pricing-section": {
      "integrity": "sha256-189d2a26a0bff378f957b6af6d3eefff9a9555d50c88eb602596ffe4c5460471",
      "fileCount": 3,
      "dependencies": [
        "@lucide/vue"
      ],
      "registryDependencies": [
        "badge",
        "button",
        "card",
        "locale-zh-cn",
        "result"
      ],
      "category": "marketing",
      "examples": []
    },
    "progress": {
      "integrity": "sha256-765c0ace7c9605f4054d3e1add0deaf6165b174c5fe2f8b107871a7b065fde53",
      "fileCount": 3,
      "dependencies": [
        "reka-ui"
      ],
      "registryDependencies": [],
      "category": "feedback",
      "examples": []
    },
    "radio-group": {
      "integrity": "sha256-e2083937f5d4b2b0b5663481bb08343c1a247115770ffc82d123f8a4c3d0eb47",
      "fileCount": 4,
      "dependencies": [
        "@lucide/vue",
        "reka-ui"
      ],
      "registryDependencies": [],
      "category": "form",
      "examples": []
    },
    "rate": {
      "integrity": "sha256-a0b921f69962e0671c8ad72dc4bcff6bf0b2a86604868d9e6fd9666b19de725d",
      "fileCount": 2,
      "dependencies": [
        "@lucide/vue"
      ],
      "registryDependencies": [],
      "category": "form",
      "examples": []
    },
    "result": {
      "integrity": "sha256-84c0cee46821ccd7ac6905347046a8ae549b2a031f1f7326a324ff5352f60eb0",
      "fileCount": 2,
      "dependencies": [
        "@lucide/vue"
      ],
      "registryDependencies": [],
      "category": "feedback",
      "examples": []
    },
    "scratch-card": {
      "integrity": "sha256-4e051047a462b23520b75cb64ec410ebadb0521bc24b9c25e98f5edfbcd469a9",
      "fileCount": 8,
      "dependencies": [],
      "registryDependencies": [
        "locale-zh-cn"
      ],
      "category": "visual-effect",
      "examples": []
    },
    "scroll-area": {
      "integrity": "sha256-bbaa7b4bf3cbe428eb2dffb754fe7c297525f9ba3f6912dc0cfd1b8b89753d28",
      "fileCount": 3,
      "dependencies": [
        "reka-ui"
      ],
      "registryDependencies": [],
      "category": "layout",
      "examples": []
    },
    "select": {
      "integrity": "sha256-5dcbf8a57555d54f5ede63e9c9ec72f0e3e1a937f40263cac18d73268cae6e9a",
      "fileCount": 13,
      "dependencies": [
        "@lucide/vue",
        "reka-ui"
      ],
      "registryDependencies": [],
      "category": "form",
      "examples": []
    },
    "separator": {
      "integrity": "sha256-6b04bc1a75b205a0ddced988f766332e313b576135e13746cc7725a96690fde4",
      "fileCount": 2,
      "dependencies": [
        "reka-ui"
      ],
      "registryDependencies": [],
      "category": "layout",
      "examples": []
    },
    "sheet": {
      "integrity": "sha256-35dd4b5c1388c78334be1a89f1577cb9b191f031cf4cc900192f90c70064e4bb",
      "fileCount": 10,
      "dependencies": [
        "@lucide/vue",
        "reka-ui"
      ],
      "registryDependencies": [
        "locale-zh-cn"
      ],
      "category": "overlay",
      "examples": []
    },
    "skeleton": {
      "integrity": "sha256-8bf41a92e0248f1b7f04274586f6144f17f2fd8a531f9d4036307593a2679e54",
      "fileCount": 6,
      "dependencies": [],
      "registryDependencies": [],
      "category": "feedback",
      "examples": []
    },
    "sketchy-chart": {
      "integrity": "sha256-5f6232a6a1eef3ea3c3b6720da7687d42a00d1094dd80ddddf06811677676b03",
      "fileCount": 4,
      "dependencies": [],
      "registryDependencies": [
        "locale-zh-cn"
      ],
      "category": "data-display",
      "examples": []
    },
    "slider": {
      "integrity": "sha256-89b048ac4b9570fb6159b92e04301ebe27f89c42f81d5f7c4f338f96c3330cc1",
      "fileCount": 3,
      "dependencies": [
        "reka-ui"
      ],
      "registryDependencies": [],
      "category": "form",
      "examples": []
    },
    "spinner": {
      "integrity": "sha256-1a4e412bf9e699bc8c1f5e9e69c10fd0e30122d8e445f564b829628bb579c7c5",
      "fileCount": 6,
      "dependencies": [],
      "registryDependencies": [
        "locale-zh-cn"
      ],
      "category": "feedback",
      "examples": []
    },
    "stepper": {
      "integrity": "sha256-07f33b9e7560346af1b35196c0079ff69440fdd2b25408234e6e405319ac4e18",
      "fileCount": 5,
      "dependencies": [
        "@lucide/vue"
      ],
      "registryDependencies": [
        "locale-zh-cn"
      ],
      "category": "navigation",
      "examples": []
    },
    "switch": {
      "integrity": "sha256-aeb033451601fcab70915ee45b9cef7860efa433501aaf3c334c3c64d22c9a49",
      "fileCount": 5,
      "dependencies": [
        "reka-ui"
      ],
      "registryDependencies": [
        "locale-zh-cn"
      ],
      "category": "form",
      "examples": []
    },
    "table": {
      "integrity": "sha256-59d7db2b0f1711debe3e38751ea8589ca42ab896c8ea62216b12c2fb7f37cf7a",
      "fileCount": 9,
      "dependencies": [],
      "registryDependencies": [],
      "category": "data-display",
      "examples": []
    },
    "tabs": {
      "integrity": "sha256-b355a6a86b51a4e3ec378f241ed5117c3e38316dbb97a8cf6d4e0b493379a6e8",
      "fileCount": 8,
      "dependencies": [
        "reka-ui"
      ],
      "registryDependencies": [
        "card",
        "locale-zh-cn",
        "result"
      ],
      "category": "navigation",
      "examples": []
    },
    "tags-input": {
      "integrity": "sha256-8e5d2f8b91f654e4c8c87594d722ebe9044cdc623bf8951361d32d317a75db07",
      "fileCount": 8,
      "dependencies": [
        "@lucide/vue",
        "reka-ui"
      ],
      "registryDependencies": [
        "locale-zh-cn"
      ],
      "category": "form",
      "examples": []
    },
    "textarea": {
      "integrity": "sha256-1a02d4996ea6eca729cc5f672b669070351967d151afa9cb66f0ab28421ce56b",
      "fileCount": 4,
      "dependencies": [],
      "registryDependencies": [
        "input",
        "locale-zh-cn"
      ],
      "category": "form",
      "examples": []
    },
    "timeline": {
      "integrity": "sha256-e1eba8c52b181ccb5dbd7ec3e03a3cf00ab6a6f592dad70010f1d24e75c4c242",
      "fileCount": 9,
      "dependencies": [
        "@lucide/vue",
        "reka-ui"
      ],
      "registryDependencies": [
        "locale-zh-cn"
      ],
      "category": "data-display",
      "examples": []
    },
    "toast": {
      "integrity": "sha256-32644d91048da5cee52fac530955c49d8b0e386a73d498bb2fe24b0740f23ef5",
      "fileCount": 8,
      "dependencies": [
        "@lucide/vue"
      ],
      "registryDependencies": [
        "button",
        "locale-zh-cn"
      ],
      "category": "feedback",
      "examples": []
    },
    "toggle": {
      "integrity": "sha256-a26e97f8bee4b8e16d822f3f3234222437c8373421aad927799c0850a8f7fd96",
      "fileCount": 4,
      "dependencies": [
        "reka-ui"
      ],
      "registryDependencies": [],
      "category": "action",
      "examples": []
    },
    "toggle-group": {
      "integrity": "sha256-5d207bfd03f81f01ae80eb86eba63599eb01fd4f2920d2681aaca99096c7704d",
      "fileCount": 3,
      "dependencies": [
        "reka-ui"
      ],
      "registryDependencies": [
        "toggle"
      ],
      "category": "action",
      "examples": []
    },
    "tooltip": {
      "integrity": "sha256-db77c12d18fac3f8ef88bbae5837d93bbb4529d86184846368506d094ebeae47",
      "fileCount": 4,
      "dependencies": [
        "reka-ui"
      ],
      "registryDependencies": [],
      "category": "overlay",
      "examples": []
    },
    "tour": {
      "integrity": "sha256-5b96dd92025be6a327f7568ddc938fb05c327a66202160fc4e8d7320d6df70bd",
      "fileCount": 5,
      "dependencies": [],
      "registryDependencies": [
        "locale-zh-cn"
      ],
      "category": "overlay",
      "examples": []
    },
    "transfer": {
      "integrity": "sha256-6428ea7fe44cedf1a9260f3edce58aaee6c398c0e800ef83a3fc74619f61f80d",
      "fileCount": 4,
      "dependencies": [
        "@lucide/vue"
      ],
      "registryDependencies": [
        "button",
        "card",
        "checkbox",
        "input",
        "locale-zh-cn"
      ],
      "category": "form",
      "examples": []
    },
    "tree-select": {
      "integrity": "sha256-d830816d5fe51b2d7e34a93f102877cfe81ba1a6d7997ca81c5948ca5db99e47",
      "fileCount": 13,
      "dependencies": [
        "@lucide/vue",
        "reka-ui"
      ],
      "registryDependencies": [
        "input",
        "locale-zh-cn",
        "popover"
      ],
      "category": "form",
      "examples": []
    },
    "tree-view": {
      "integrity": "sha256-32fe75bbed196effe1656d53d7c228bfc5b50744cee9d782b9a71e60b4c0c567",
      "fileCount": 9,
      "dependencies": [
        "@lucide/vue",
        "reka-ui"
      ],
      "registryDependencies": [
        "checkbox",
        "locale-zh-cn"
      ],
      "category": "data-display",
      "examples": []
    },
    "typewriter-text": {
      "integrity": "sha256-ebdfef26d96be609085197fbc02fbc2253e8166376d458327cf39384e1ad7d9a",
      "fileCount": 4,
      "dependencies": [],
      "registryDependencies": [],
      "category": "visual-effect",
      "examples": []
    },
    "upload": {
      "integrity": "sha256-73b7109b76f363b2ccfe2213818aa3470f36949d0fef8f6d891ed602907e60c4",
      "fileCount": 6,
      "dependencies": [
        "@lucide/vue"
      ],
      "registryDependencies": [],
      "category": "form",
      "examples": []
    },
    "virtual-scroll": {
      "integrity": "sha256-cd5254fba1ab307f02dfc0e57a6d37b5cedca0df670d8af836def3ffeb3aa3b0",
      "fileCount": 4,
      "dependencies": [
        "@tanstack/vue-virtual"
      ],
      "registryDependencies": [
        "locale-zh-cn"
      ],
      "category": "utility",
      "examples": []
    },
    "watermark": {
      "integrity": "sha256-9c95aac240ef661b18eb98c01de2c0d8e413176d69e7de8d7678ca3726c88c76",
      "fileCount": 2,
      "dependencies": [],
      "registryDependencies": [],
      "category": "utility",
      "examples": []
    }
  },
  "integrity": "1538c8894e66d2f2a4fb87b42a7df8e971c4c313a2c8dab4da4a9c6aff929ad2"
}